[{"note":"blue indeed","discountRate":"0.5","description":"blue mallet","sellPrice":"9.99","id":"1","position":"234-adf-3443","availableQty":"50","barCode":"1"},{"note":"red indeed","discountRate":"0.2","description":"red ball","sellPrice":"7.79","id":"2","position":"2334-abf-343","availableQty":"5","barCode":"2"},{"note":null,"discountRate":"0","description":"chair","sellPrice":"19.99","id":"3","position":"434-atf-3443","availableQty":"1","barCode":"3"},{"note":"dog food","discountRate":"0.1","description":"dentasticks","sellPrice":"8.99","id":"4","position":"234-add-3443","availableQty":"10","barCode":"4"},{"discountRate":"0.0","Note":"","description":"fdsds","sellPrice":"8.9","availableQty":"0","id":"3432","barCode":"3432"},{"discountRate":"0.0","Note":"","description":"kfjdlks","sellPrice":"3.0","availableQty":"0","id":"3421","barCode":"3421"},{"discountRate":"0.0","Note":"note","description":"product","sellPrice":"432.0","availableQty":"0","id":"32","barCode":"32"},{"discountRate":"0.0","Note":"","description":"gdas","sellPrice":"0.0","id":"423","availableQty":"0","barCode":"423"},{"discountRate":"0.0","Note":"note","description":"prodescr","sellPrice":"0.0","id":"563","availableQty":"0","barCode":"563"},{"discountRate":"0.2","note":"red indeed","description":"red ball","sellPrice":"0.2","id":"2","availableQty":"5","barCode":"2"},{"discountRate":"0.0","note":"","description":"fdsds","sellPrice":"0.0","id":"3432","availableQty":"0","barCode":"3432"},{"discountRate":"0.0","note":"added note","description":"kfjdlks","sellPrice":"0.0","id":"3421","availableQty":"0","barCode":"3421"}]